DRSpy/__init__.py
DRSpy/data_struct.py
DRSpy/main.py
DRSpy/optimize.py
DRSpy-1.0.dist-info/METADATA
DRSpy-1.0.dist-info/WHEEL
DRSpy-1.0.dist-info/entry_points.txt
DRSpy-1.0.dist-info/top_level.txt
DRSpy-1.0.dist-info/RECORD
