Metadata-Version: 2.1
Name: DRSpy
Version: 1.0
Summary: Data loader for DRS4-psi
Home-page: https://github.com/aszadzinski/scripts-and-notes/tree/master/python/DRS4-PSI
Author: aszadzinski
Author-email: UNKNOWN
License: MIT
Platform: UNKNOWN
Requires: click
Requires: pandas
Requires: matplotlib
Requires: scipy
Requires-Dist: click
Requires-Dist: matplotlib
Requires-Dist: pandas
Requires-Dist: scipy
